akskubeconfig/__init__.py
akskubeconfig/command.py
akskubeconfig/errors.py
akskubeconfig/helpers.py
akskubeconfig/test_command.py
akskubeconfig/test_errors.py
akskubeconfig/test_helpers.py
akskubeconfig/test_types.py
akskubeconfig/types.py
akskubeconfig-1.1.1.dist-info/METADATA
akskubeconfig-1.1.1.dist-info/WHEEL
akskubeconfig-1.1.1.dist-info/entry_points.txt
akskubeconfig-1.1.1.dist-info/licenses/LICENSE
akskubeconfig-1.1.1.dist-info/RECORD
