Metadata-Version: 2.4
Name: akskubeconfig
Version: 1.1.1
Summary: A utility to generate kubeconfig for AKS clusters in bulk across one or multiple subscriptions
License: MIT
License-File: LICENSE
Keywords: aks,kubeconfig,kubernetes
Author: Cameron Larsen
Author-email: cameron.larsen@nielseniq.com
Requires-Python: >=3.10,<4.0
Classifier: License :: OSI Approved :: MIT License
Classifier: Programming Language :: Python :: 3
Classifier: Programming Language :: Python :: 3.10
Classifier: Programming Language :: Python :: 3.11
Classifier: Programming Language :: Python :: 3.12
Classifier: Programming Language :: Python :: 3.13
Classifier: Programming Language :: Python :: 3.14
Requires-Dist: PyYAML (>=6.0.2,<7.0.0)
Requires-Dist: azure-identity (>=1.19.0,<2.0.0)
Requires-Dist: azure-mgmt-containerservice (>=32,<41)
Requires-Dist: azure-mgmt-subscription (>=3.1.1,<4.0.0)
Project-URL: Repository, https://github.com/niq-ccoe-platform-engineering/akskubeconfig
